fastapi_orm_ext/__about__.py
fastapi_orm_ext/__init__.py
fastapi_orm_ext/errors.py
fastapi_orm_ext/py.typed
fastapi_orm_ext/repository.py
fastapi_orm_ext/table/__init__.py
fastapi_orm_ext/table/_table.py
fastapi_orm_ext/table/mixins.py
fastapi_orm_ext/table/sqltypes.py
fastapi_orm_ext-0.1.0.dist-info/METADATA
fastapi_orm_ext-0.1.0.dist-info/WHEEL
fastapi_orm_ext-0.1.0.dist-info/licenses/LICENSE
fastapi_orm_ext-0.1.0.dist-info/RECORD
