Metadata-Version: 2.4
Name: fastapi-orm-ext
Version: 0.1.0
Summary: FastAPI ORM Extensions
Project-URL: Documentation, https://github.com/pkozhem/fastapi-orm-ext#readme
Project-URL: Issues, https://github.com/pkozhem/fastapi-orm-ext/issues
Project-URL: Source, https://github.com/pkozhem/fastapi-orm-ext
Project-URL: Repository, https://github.com/pkozhem/fastapi-orm-ext
Author-email: Pavel Kozhemjachenko <pkozhem@gmail.com>
License-Expression: MIT
License-File: LICENSE
Keywords: extensions,fastapi,orm
Classifier: Programming Language :: Python
Classifier: Programming Language :: Python :: 3.13
Classifier: Programming Language :: Python :: Implementation :: CPython
Classifier: Programming Language :: Python :: Implementation :: PyPy
Requires-Python: >=3.13
Requires-Dist: fastapi>=0.116.1
Requires-Dist: sqlalchemy>=2.0.41
